hiworld/__init__.py
hiworld123-0.1.0.dist-info/METADATA
hiworld123-0.1.0.dist-info/WHEEL
hiworld123-0.1.0.dist-info/top_level.txt
hiworld123-0.1.0.dist-info/RECORD
