Metadata-Version: 2.4
Name: hiworld123
Version: 0.1.0
Summary: Simple HiWorld library
Author: MaksVavrik
Requires-Python: >=3.6
Dynamic: author
Dynamic: requires-python
Dynamic: summary
